{"name":"genitore","children":[{"name":"NonCensurato","children":[{"name":"Zerocensorship","sottotitolo":"WATCH: ISIS Burning Jordanian Pilot ALIVE - Uncut Video","value":59,"url":"graphic.html"},{"name":"FoxNews","sottotitolo":"WARNING, EXTREMELY GRAPHIC VIDEO: ISIS burns hostage alive","value":34,"url":"graphic.html"},{"name":"Leaksource","sottotitolo":"Jordanian Pilot Kaseasbeh Burned Alive by Islamic State; Jordan Executes IS Requested Prisoner Rishawi in\u00a0Response","value":30,"url":"graphic.html"}]},{"name":"SemiCensurato","children":[{"name":"CBS","sottotitolo":"ISIS video purports to show Jordanian pilot burned alive","value":34,"url":"cbs.html"},{"name":"Miseeharris","sottotitolo":"ISIS Strikes Again Burning Jordanian Pilot Alive","value":25,"url":"miseeharris.html"}]},{"name":"Censurato","children":[{"name":"SkyNews","sottotitolo":"ISIS Release Video TORCHING Captive to Death in a Cage","value":21,"url":"skynews1.html"},{"name":"FoxNews","sottotitolo":"ISIS video purportedly shows execution of Jordanian pilot","value":20,"url":"foxnews2.html"},{"name":"CNN","sottotitolo":"ISIS claims to have burned Jordanian hostage alive","value":28,"url":"cnn.html"},{"name":"SkyNews","sottotitolo":"ISIS Jordanian Pilot Burned Alive In Video, Mu'ath Al Kassasbeh Executed by ISIS","value":15,"url":"skynews2.html"},{"name":"Reuters","sottotitolo":"Islamic State shows burning of hostage, Jordan vows 'earth-shaking' response","value":15,"url":"reuters.html"},{"name":"NBC","sottotitolo":"Burned Alive:\u00a0ISIS\u00a0Video Purports to Show Murder of Jordanian Pilot","value":15,"url":"nbc.html"}]}]}