{"nodes":[{"label":"http://www.artstor.org/terms","x":-177.80667114257812,"y":-86.7032699584961,"id":"158","attributes":{"in_network":"false"},"color":"rgb(6,109,89)","size":2.446545124053955},{"label":"http://www.ucla.edu/","x":60.994258880615234,"y":-188.18174743652344,"id":"13","attributes":{"in_network":"true"},"color":"rgb(6,109,89)","size":2.446545124053955},{"label":"http://www.ala.org/yalsa/","x":-89.42545318603516,"y":-176.45327758789062,"id":"175","attributes":{"in_network":"false"},"color":"rgb(6,109,89)","size":2.446545124053955},{"label":"http://www.mcgill.ca/library/services/request-scan","x":152.89524841308594,"y":125.5217514038086,"id":"72","attributes":{"in_network":"false"},"color":"rgb(6,109,89)","size":2.446545124053955},{"label":"library.ubc.ca","x":108.82085418701172,"y":165.19894409179688,"id":"82","attributes":{"inlinksfromcrawl":"5","authority":"516","in_network":"true","category":"CA","tld":"ca","sldtld":"ca","knowledge":"1"},"color":"rgb(6,109,89)","size":4.745100021362305},{"label":"http://chroniclingamerica.loc.gov/search/titles/results/?terms\u003dmichigan","x":-195.5292510986328,"y":30.016355514526367,"id":"142","attributes":{"in_network":"false"},"color":"rgb(6,109,89)","size":2.446545124053955},{"label":"http://mcgill.worldcat.org/webservices/root/search/lists","x":196.4622802734375,"y":23.13530921936035,"id":"53","attributes":{"in_network":"false"},"color":"rgb(6,109,89)","size":2.446545124053955},{"label":"umd.libanswers.com","x":-94.06890106201172,"y":30.564838409423828,"id":"9","attributes":{"ordine":"03","inlinksfromcrawl":"361","authority":"2012","in_network":"true","category":"COM","tld":"com","sldtld":"com","knowledge":"1"},"color":"rgb(6,109,89)","size":11.409127235412598},{"label":"questionpoint.org","x":94.06890106201172,"y":-30.564838409423828,"id":"26","attributes":{"ordine":"08","inlinksfromcrawl":"17","authority":"1002","in_network":"true","category":"ORG","tld":"org","sldtld":"org","knowledge":"0"},"color":"rgb(6,109,89)","size":6.910017490386963},{"label":"http://www.oecdtokyo.org/","x":162.94476318359375,"y":-112.16804504394531,"id":"32","attributes":{"in_network":"true"},"color":"rgb(6,109,89)","size":2.446545124053955},{"label":"http://mcgill.ca/newsroom/channels/news/two-rhodes-264300","x":185.0767059326172,"y":69.85186004638672,"id":"61","attributes":{"in_network":"false"},"color":"rgb(6,109,89)","size":2.446545124053955},{"label":"http://www.mcgill.ca/library/services/otherloans/interlibrary","x":145.17880249023438,"y":134.371826171875,"id":"74","attributes":{"in_network":"false"},"color":"rgb(6,109,89)","size":2.446545124053955},{"label":"http://www.oecd.org/trade/","x":187.43994140625,"y":-63.23716354370117,"id":"40","attributes":{"in_network":"false"},"color":"rgb(6,109,89)","size":2.446545124053955},{"label":"spl.org","x":91.3221664428711,"y":-175.47914123535156,"id":"18","attributes":{"inlinksfromcrawl":"5","authority":"666","in_network":"true","category":"ORG","tld":"org","sldtld":"org","knowledge":"0"},"color":"rgb(6,109,89)","size":5.4132843017578125},{"label":"http://artstor.org/webinars?view\u003dSS","x":-188.672607421875,"y":-59.45854949951172,"id":"153","attributes":{"in_network":"false"},"color":"rgb(6,109,89)","size":2.446545124053955},{"label":"arxiv.org","x":-195.71669006347656,"y":-28.768827438354492,"id":"149","attributes":{"inlinksfromcrawl":"3","authority":"679","in_network":"true","category":"ORG","tld":"org","sldtld":"org","knowledge":"0"},"color":"rgb(6,109,89)","size":5.471193790435791},{"label":"http://mcgill.worldcat.org/","x":197.06234741210938,"y":17.294559478759766,"id":"52","attributes":{"in_network":"true"},"color":"rgb(6,109,89)","size":2.446545124053955},{"label":"http://www.mcgill.ca/microimm/","x":182.92213439941406,"y":75.31375122070312,"id":"62","attributes":{"in_network":"false"},"color":"rgb(6,109,89)","size":2.446545124053955},{"label":"http://www.oecd.org/tax/beps.htm","x":192.32089233398438,"y":-46.31782913208008,"id":"43","attributes":{"in_network":"false"},"color":"rgb(6,109,89)","size":2.446545124053955},{"label":"http://www.artstor.org/privacy-policy","x":-156.09706115722656,"y":-121.51698303222656,"id":"165","attributes":{"in_network":"false"},"color":"rgb(6,109,89)","size":2.446545124053955},{"label":"http://umd.libanswers.com/","x":48.42752456665039,"y":-191.800537109375,"id":"10","attributes":{"authority":"250","in_network":"true"},"color":"rgb(6,109,89)","size":3.5601861476898193},{"label":"http://www.spl.org/library-collection/articles-and-research/magazines-and-newspapers","x":104.61071014404297,"y":-167.8966064453125,"id":"20","attributes":{"in_network":"false"},"color":"rgb(6,109,89)","size":2.446545124053955},{"label":"lib.washington.edu","x":6.056484625610852E-15,"y":-98.90989685058594,"id":"84","attributes":{"ordine":"10","inlinksfromcrawl":"22","authority":"831","in_network":"true","category":"EDU","tld":"edu","sldtld":"edu","knowledge":"0"},"color":"rgb(6,109,89)","size":6.148287296295166},{"label":"http://www.lib.umd.edu/tlc/home","x":-84.52808380126953,"y":178.85098266601562,"id":"116","attributes":{"in_network":"false"},"color":"rgb(6,109,89)","size":2.446545124053955},{"label":"http://www.arl.org/","x":-145.90728759765625,"y":-133.5804443359375,"id":"167","attributes":{"authority":"180","in_network":"true"},"color":"rgb(192,192,192)","size":3.248366594314575},{"label":"http://www.washington.edu/admin/pb/home/opb-tuition.htm","x":41.40817642211914,"y":-193.43740844726562,"id":"8","attributes":{"in_network":"false"},"color":"rgb(6,109,89)","size":2.446545124053955},{"label":"http://www.lib.washington.edu/about/news/newsletter/archive/e-news-spring-2015","x":-4.964827537536621,"y":197.75747680664062,"id":"103","attributes":{"in_network":"false"},"color":"rgb(6,109,89)","size":2.446545124053955},{"label":"firstsearch.oclc.org","x":-146.72828674316406,"y":132.6781005859375,"id":"127","attributes":{"inlinksfromcrawl":"4","authority":"377","in_network":"true","category":"ORG","tld":"org","sldtld":"org","knowledge":"0"},"color":"rgb(6,109,89)","size":4.12591552734375},{"label":"http://www.spl.org/library-collection/articles-and-research/books-and-reading","x":119.12706756591797,"y":-157.92849731445312,"id":"23","attributes":{"in_network":"false"},"color":"rgb(6,109,89)","size":2.446545124053955},{"label":"oecd-ilibrary.org","x":6.056483778577905E-15,"y":98.90989685058594,"id":"45","attributes":{"ordine":"05","inlinksfromcrawl":"299","authority":"1589","in_network":"true","category":"ORG","tld":"org","sldtld":"org","knowledge":"0"},"color":"rgb(6,109,89)","size":9.524847030639648},{"label":"http://www.lib.washington.edu/","x":96.4291000366211,"y":172.72549438476562,"id":"85","attributes":{"in_network":"true"},"color":"rgb(6,109,89)","size":2.446545124053955},{"label":"http://www.lib.umd.edu/univarchives","x":-73.76807403564453,"y":183.55091857910156,"id":"114","attributes":{"in_network":"false"},"color":"rgb(6,109,89)","size":2.446545124053955},{"label":"http://arxiv.org/","x":-194.10975646972656,"y":-38.1323127746582,"id":"150","attributes":{"in_network":"true"},"color":"rgb(6,109,89)","size":2.446545124053955},{"label":"arl.org","x":-151.43258666992188,"y":-127.28252410888672,"id":"166","attributes":{"inlinksfromcrawl":"6","authority":"289","in_network":"true","category":"ORG","tld":"org","sldtld":"org","knowledge":"0"},"color":"rgb(6,109,89)","size":3.7339138984680176},{"label":"ncbi.nlm.nih.gov","x":197.7313232421875,"y":-5.915671348571777,"id":"49","attributes":{"inlinksfromcrawl":"2","authority":"715","in_network":"true","category":"GOV","tld":"gov","sldtld":"gov","knowledge":"0"},"color":"rgb(6,109,89)","size":5.631558418273926},{"label":"http://www.lib.washington.edu/static/public/teaching/instruct","x":91.2605209350586,"y":175.51121520996094,"id":"86","attributes":{"in_network":"false"},"color":"rgb(6,109,89)","size":2.446545124053955},{"label":"http://www.mcgill.ca/library/services/scan-print-copy","x":160.0730438232422,"y":116.2294692993164,"id":"70","attributes":{"in_network":"false"},"color":"rgb(6,109,89)","size":2.446545124053955},{"label":"http://www.lib.washington.edu/about/contact","x":-39.91957473754883,"y":193.75009155273438,"id":"109","attributes":{"in_network":"false"},"color":"rgb(6,109,89)","size":2.446545124053955},{"label":"http://www.artstor.org/support","x":-175.1551971435547,"y":-91.94197845458984,"id":"159","attributes":{"in_network":"false"},"color":"rgb(6,109,89)","size":2.446545124053955},{"label":"chroniclingamerica.loc.gov","x":-192.7179718017578,"y":44.63691329956055,"id":"140","attributes":{"inlinksfromcrawl":"5","authority":"589","in_network":"true","category":"GOV","tld":"gov","sldtld":"gov","knowledge":"3"},"color":"rgb(6,109,89)","size":5.070282936096191},{"label":"http://www.ncbi.nlm.nih.gov/pubmed/","x":197.78372192382812,"y":3.7769412994384766,"id":"50","attributes":{"in_network":"true"},"color":"rgb(6,109,89)","size":2.446545124053955},{"label":"dl.ndl.go.jp","x":-58.13777542114258,"y":80.01978302001953,"id":"134","attributes":{"ordine":"04","inlinksfromcrawl":"5","authority":"1789","in_network":"true","category":"GOV","tld":"jp","sldtld":"go.jp","knowledge":"0"},"color":"rgb(6,109,89)","size":10.415760040283203},{"label":"http://www.artstor.org/webinars","x":-182.63751220703125,"y":-76.00138092041016,"id":"156","attributes":{"in_network":"false"},"color":"rgb(6,109,89)","size":2.446545124053955},{"label":"oecdtokyo.org","x":157.16397094726562,"y":-120.13390350341797,"id":"31","attributes":{"inlinksfromcrawl":"2","authority":"743","in_network":"true","category":"ORG","tld":"org","sldtld":"org","knowledge":"2"},"color":"rgb(6,109,89)","size":5.756285667419434},{"label":"http://amturing.acm.org/award_winners/cerf_1083211.cfm","x":-130.75425720214844,"y":-148.44525146484375,"id":"169","attributes":{"in_network":"true"},"color":"rgb(6,109,89)","size":2.446545124053955},{"label":"http://www.ala.org/aboutala/tax584","x":-45.40872573852539,"y":-192.53756713867188,"id":"183","attributes":{"in_network":"false"},"color":"rgb(6,109,89)","size":2.446545124053955},{"label":"http://www.mcgill.ca/library/","x":193.37095642089844,"y":41.71738815307617,"id":"56","attributes":{"in_network":"true"},"color":"rgb(6,109,89)","size":2.446545124053955},{"label":"ucla.edu","x":94.06890106201172,"y":30.564838409423828,"id":"12","attributes":{"ordine":"07","inlinksfromcrawl":"454","authority":"1201","in_network":"true","category":"EDU","tld":"edu","sldtld":"edu","knowledge":"0"},"color":"rgb(6,109,89)","size":7.796475887298584},{"label":"http://www.mcgill.ca/library/webdirectory","x":180.60641479492188,"y":80.70928955078125,"id":"63","attributes":{"in_network":"false"},"color":"rgb(6,109,89)","size":2.446545124053955},{"label":"http://www.ucla.edu/about/awards-and-honors/faculty-honors","x":77.48735809326172,"y":-182.01202392578125,"id":"16","attributes":{"in_network":"false"},"color":"rgb(6,109,89)","size":2.446545124053955},{"label":"http://mcgill.worldcat.org/default.jsp","x":195.6891326904297,"y":28.955677032470703,"id":"54","attributes":{"in_network":"false"},"color":"rgb(6,109,89)","size":2.446545124053955},{"label":"http://www.questionpoint.org/crs/servlet/org.oclc.admin.BuildForm?\u0026institution\u003d10082\u0026type\u003d1\u0026language\u003d1","x":134.4578857421875,"y":-145.09909057617188,"id":"27","attributes":{"in_network":"true"},"color":"rgb(6,109,89)","size":2.446545124053955},{"label":"bl.uk","x":-197.55880737304688,"y":-10.158170700073242,"id":"147","attributes":{"inlinksfromcrawl":"2","authority":"432","in_network":"true","category":"UK","tld":"uk","sldtld":"uk","knowledge":"0"},"color":"rgb(6,109,89)","size":4.370916843414307},{"label":"http://www.washington.edu/","x":12.350110054016113,"y":-197.43389892578125,"id":"3","attributes":{"in_network":"true"},"color":"rgb(6,109,89)","size":2.446545124053955},{"label":"http://www.mcgill.ca/library/services/teaching/course-reserves/request","x":175.49984741210938,"y":91.28238677978516,"id":"65","attributes":{"in_network":"false"},"color":"rgb(6,109,89)","size":2.446545124053955},{"label":"http://www.mcgill.ca/library/services/teaching/class-screening","x":172.71348571777344,"y":96.45061492919922,"id":"66","attributes":{"in_network":"false"},"color":"rgb(6,109,89)","size":2.446545124053955},{"label":"allaboutcookies.org","x":-119.9731674194336,"y":-157.28671264648438,"id":"171","attributes":{"inlinksfromcrawl":"2","authority":"412","in_network":"true","category":"ORG","tld":"org","sldtld":"org","knowledge":"1"},"color":"rgb(6,109,89)","size":4.281825065612793},{"label":"crl.edu","x":-182.92054748535156,"y":75.31759643554688,"id":"136","attributes":{"inlinksfromcrawl":"7","authority":"499","in_network":"true","category":"EDU","tld":"edu","sldtld":"edu","knowledge":"2"},"color":"rgb(6,109,89)","size":4.66937255859375},{"label":"http://www.spl.org/library-collection/articles-and-research/local-history","x":109.54742431640625,"y":-164.71803283691406,"id":"21","attributes":{"in_network":"false"},"color":"rgb(6,109,89)","size":2.446545124053955},{"label":"http://catalog.loc.gov/","x":-197.29966735839844,"y":14.335572242736816,"id":"144","attributes":{"authority":"650","in_network":"true"},"color":"rgb(6,109,89)","size":5.342011451721191},{"label":"http://www.lib.washington.edu/dean","x":30.14697265625,"y":195.5091552734375,"id":"97","attributes":{"in_network":"false"},"color":"rgb(6,109,89)","size":2.446545124053955},{"label":"http://www.library.ucla.edu/LuxLab","x":115.92190551757812,"y":160.29591369628906,"id":"81","attributes":{"in_network":"false"},"color":"rgb(6,109,89)","size":2.446545124053955},{"label":"http://www.worldcat.org/","x":6.485276222229004,"y":-197.7134552001953,"id":"1","attributes":{"in_network":"true"},"color":"rgb(6,109,89)","size":2.446545124053955},{"label":"http://www.ala.org/irrt/","x":-67.89506530761719,"y":-185.803466796875,"id":"179","attributes":{"in_network":"false"},"color":"rgb(6,109,89)","size":2.446545124053955},{"label":"http://www.lib.umd.edu/tlc/tlc-tech-desk","x":-79.1829605102539,"y":181.28079223632812,"id":"115","attributes":{"in_network":"false"},"color":"rgb(6,109,89)","size":2.446545124053955},{"label":"http://www.lib.umd.edu/tlc/equipment-availability","x":-100.0981674194336,"y":170.62539672851562,"id":"119","attributes":{"in_network":"false"},"color":"rgb(6,109,89)","size":2.446545124053955},{"label":"http://www.crl.edu/print/6953","x":-190.48300170898438,"y":53.37503433227539,"id":"139","attributes":{"in_network":"false","category":""},"color":"rgb(6,109,89)","size":2.446545124053955},{"label":"http://www.mcgill.ca/library/services/research","x":156.5531005859375,"y":120.92887878417969,"id":"71","attributes":{"in_network":"false"},"color":"rgb(6,109,89)","size":2.446545124053955},{"label":"http://umd.libanswers.com/ask","x":55.38258361816406,"y":-189.90902709960938,"id":"11","attributes":{"in_network":"false"},"color":"rgb(6,109,89)","size":2.446545124053955},{"label":"http://www.spl.org/library-collection/articles-and-research/genealogy","x":114.38763427734375,"y":-161.3943634033203,"id":"22","attributes":{"in_network":"false"},"color":"rgb(6,109,89)","size":2.446545124053955},{"label":"http://www.lib.washington.edu/about","x":-51.344322204589844,"y":191.04039001464844,"id":"111","attributes":{"in_network":"false"},"color":"rgb(6,109,89)","size":2.446545124053955},{"label":"aeaweb.org","x":-38.149505615234375,"y":-194.1063690185547,"id":"184","attributes":{"inlinksfromcrawl":"2","authority":"291","in_network":"true","category":"ORG","tld":"org","sldtld":"org","knowledge":"0"},"color":"rgb(6,109,89)","size":3.7428231239318848},{"label":"http://www.lib.washington.edu/ill/faq","x":41.69329833984375,"y":193.37615966796875,"id":"95","attributes":{"in_network":"false"},"color":"rgb(6,109,89)","size":2.446545124053955},{"label":"http://www.oecd.org/unitedkingdom/","x":181.07369995117188,"y":-79.65541076660156,"id":"37","attributes":{"in_network":"false"},"color":"rgb(6,109,89)","size":2.446545124053955},{"label":"http://www.spl.org/","x":99.58184051513672,"y":-170.92726135253906,"id":"19","attributes":{"in_network":"true"},"color":"rgb(6,109,89)","size":2.446545124053955},{"label":"http://www.washington.edu/students/servicesforstudents/","x":18.204063415527344,"y":-196.98040771484375,"id":"4","attributes":{"in_network":"false"},"color":"rgb(6,109,89)","size":2.446545124053955},{"label":"http://www.artstor.org/webinars?order\u003dtitle\u0026sort\u003ddesc","x":-186.82489013671875,"y":-65.03173828125,"id":"154","attributes":{"in_network":"false"},"color":"rgb(6,109,89)","size":2.446545124053955},{"label":"http://www.lib.washington.edu/search","x":69.82880401611328,"y":185.0854034423828,"id":"90","attributes":{"in_network":"false"},"color":"rgb(6,109,89)","size":2.446545124053955},{"label":"http://www.ala.org/news/member-news/2016/11/acrl-ala-arl-joint-advisory-task-force-continues-clarify-academic-library","x":-78.79906463623047,"y":-181.447998046875,"id":"177","attributes":{"in_network":"false"},"color":"rgb(6,109,89)","size":2.446545124053955},{"label":"http://www.artstor.org/resources-overview","x":-159.63465881347656,"y":-116.83084869384766,"id":"164","attributes":{"in_network":"false"},"color":"rgb(6,109,89)","size":2.446545124053955},{"label":"http://www.mcgill.ca/oss/","x":188.89495849609375,"y":58.748329162597656,"id":"59","attributes":{"in_network":"false"},"color":"rgb(6,109,89)","size":2.446545124053955},{"label":"e-stat.go.jp","x":-161.33096313476562,"y":114.47702026367188,"id":"130","attributes":{"inlinksfromcrawl":"2","authority":"786","in_network":"true","category":"GOV","tld":"jp","sldtld":"go.jp","knowledge":"0"},"color":"rgb(6,109,89)","size":5.947832107543945},{"label":"http://www.lib.washington.edu/about/employment/fellowships/guy-and-charlotte-springsteel-graduate-fellowship","x":-22.531471252441406,"y":196.53244018554688,"id":"106","attributes":{"in_network":"false"},"color":"rgb(6,109,89)","size":2.446545124053955},{"label":"http://www.artstor.org/shared-shelf/subscribers","x":-166.28494262695312,"y":-107.15402221679688,"id":"162","attributes":{"in_network":"false"},"color":"rgb(6,109,89)","size":2.446545124053955},{"label":"http://www.ala.org/lhrt/","x":-73.37938690185547,"y":-183.70664978027344,"id":"178","attributes":{"in_network":"false"},"color":"rgb(6,109,89)","size":2.446545124053955},{"label":"http://www.mcgill.ca/library/services/studyareas","x":166.6868896484375,"y":106.52769470214844,"id":"68","attributes":{"in_network":"false"},"color":"rgb(6,109,89)","size":2.446545124053955},{"label":"http://www.ala.org/ascla/","x":-62.35093307495117,"y":-187.73660278320312,"id":"180","attributes":{"in_network":"false"},"color":"rgb(6,109,89)","size":2.446545124053955},{"label":"http://www.aeaweb.org/","x":-27.78095817565918,"y":-195.85935974121094,"id":"185","attributes":{"authority":"578","in_network":"true","category":""},"color":"rgb(192,192,192)","size":5.021283149719238},{"label":"http://www.washington.edu/directory/","x":29.85871696472168,"y":-195.5533905029297,"id":"6","attributes":{"in_network":"false"},"color":"rgb(6,109,89)","size":2.446545124053955},{"label":"http://www.artstor.org/sharedshelf","x":-172.3494110107422,"y":-97.09969329833984,"id":"160","attributes":{"in_network":"false"},"color":"rgb(6,109,89)","size":2.446545124053955},{"label":"http://www.oecd.org/tax/tax-revenues-reach-new-high-as-the-tax-mix-shifts-further-towards-labour-and-consumption-taxes.htm","x":190.861572265625,"y":-52.00508117675781,"id":"42","attributes":{"in_network":"false"},"color":"rgb(6,109,89)","size":2.446545124053955},{"label":"http://www.lib.washington.edu/about/strategicplan/2014/directions/full","x":12.641157150268555,"y":197.4154815673828,"id":"100","attributes":{"in_network":"false"},"color":"rgb(6,109,89)","size":2.446545124053955},{"label":"http://www.lib.umd.edu/tlc/equipment","x":-89.79875183105469,"y":176.2635955810547,"id":"117","attributes":{"in_network":"false"},"color":"rgb(6,109,89)","size":2.446545124053955},{"label":"http://www.mcgill.ca/library/services/workshops","x":178.131591796875,"y":86.03373718261719,"id":"64","attributes":{"in_network":"false"},"color":"rgb(6,109,89)","size":2.446545124053955},{"label":"http://www.lib.umd.edu/tlc","x":-105.11785888671875,"y":167.5795440673828,"id":"120","attributes":{"in_network":"false"},"color":"rgb(6,109,89)","size":2.446545124053955},{"label":"catalog.library.ucla.edu","x":-197.76983642578125,"y":4.445578098297119,"id":"145","attributes":{"inlinksfromcrawl":"36","authority":"104","in_network":"true","category":"EDU","tld":"edu","sldtld":"edu","knowledge":"0"},"color":"rgb(6,109,89)","size":2.9098198413848877},{"label":"http://www.mcgill.ca/library/services/teaching","x":169.77496337890625,"y":101.53387451171875,"id":"67","attributes":{"in_network":"false"},"color":"rgb(6,109,89)","size":2.446545124053955},{"label":"http://amturing.acm.org/award_winners/pearl_2658896.cfm","x":-126.29114532470703,"y":-152.26034545898438,"id":"170","attributes":{"in_network":"true"},"color":"rgb(6,109,89)","size":2.446545124053955},{"label":"http://www.ucla.edu/academics/libraries","x":72.05152130126953,"y":-184.23150634765625,"id":"15","attributes":{"in_network":"false"},"color":"rgb(6,109,89)","size":2.446545124053955},{"label":"http://www.oecd.org/","x":173.2726287841797,"y":-95.44245910644531,"id":"34","attributes":{"in_network":"true"},"color":"rgb(6,109,89)","size":2.446545124053955},{"label":"http://www.ndltd.org/","x":197.20419311523438,"y":-15.59408187866211,"id":"48","attributes":{"in_network":"true"},"color":"rgb(6,109,89)","size":2.446545124053955},{"label":"http://www.ala.org/acrl/aboutacrl/directoryofleadership/sections/sts/stswebsite/mentors/mentorinfo","x":-56.751869201660156,"y":-189.50433349609375,"id":"181","attributes":{"in_network":"false"},"color":"rgb(192,192,192)","size":2.446545124053955},{"label":"http://www.ala.org/aboutala/tax591","x":-51.102806091308594,"y":-191.10513305664062,"id":"182","attributes":{"in_network":"false"},"color":"rgb(6,109,89)","size":2.446545124053955},{"label":"http://dl.ndl.go.jp/?__lang\u003den","x":-179.12298583984375,"y":83.95011901855469,"id":"135","attributes":{"authority":"167","in_network":"true"},"color":"rgb(6,109,89)","size":3.190457344055176},{"label":"http://www.lib.washington.edu/scholpub/facts/faq","x":58.72480010986328,"y":188.9022674560547,"id":"92","attributes":{"in_network":"false"},"color":"rgb(6,109,89)","size":2.446545124053955},{"label":"http://www.artstor.org/webinars?order\u003dfield_date_1\u0026sort\u003ddesc","x":-184.81260681152344,"y":-70.5476303100586,"id":"155","attributes":{"in_network":"false"},"color":"rgb(6,109,89)","size":2.446545124053955},{"label":"http://www.ucla.edu/about/awards-and-honors/alumni-and-student-honors","x":82.85493469238281,"y":-179.6322021484375,"id":"17","attributes":{"in_network":"false"},"color":"rgb(6,109,89)","size":2.446545124053955},{"label":"http://www.ucla.edu/research/libraries","x":66.55220794677734,"y":-186.28868103027344,"id":"14","attributes":{"in_network":"false"},"color":"rgb(6,109,89)","size":2.446545124053955},{"label":"http://www.artstor.org/shared-shelf/?q\u003duser","x":-163.0316162109375,"y":-112.04178619384766,"id":"163","attributes":{"in_network":"false"},"color":"rgb(6,109,89)","size":2.446545124053955},{"label":"ala.org","x":-103.2467269897461,"y":-168.73880004882812,"id":"173","attributes":{"inlinksfromcrawl":"3","authority":"765","in_network":"true","category":"ORG","tld":"org","sldtld":"org","knowledge":"0"},"color":"rgb(6,109,89)","size":5.854286193847656},{"label":"http://www.lib.washington.edu/about/news/newsletter","x":-16.688905715942383,"y":197.11456298828125,"id":"105","attributes":{"in_network":"false"},"color":"rgb(6,109,89)","size":2.446545124053955},{"label":"get.adobe.com","x":-133.9254913330078,"y":145.59063720703125,"id":"125","attributes":{"inlinksfromcrawl":"53","authority":"229","in_network":"true","category":"COM","tld":"com","sldtld":"com","knowledge":"0"},"color":"rgb(192,192,192)","size":3.4666402339935303},{"label":"ndltd.org","x":196.20294189453125,"y":-25.240354537963867,"id":"47","attributes":{"inlinksfromcrawl":"4","authority":"716","in_network":"true","category":"ORG","tld":"org","sldtld":"org","knowledge":"0"},"color":"rgb(6,109,89)","size":5.636012554168701},{"label":"http://get.adobe.com/flashplayer/","x":-140.19654846191406,"y":139.56216430664062,"id":"126","attributes":{"authority":"300","in_network":"true"},"color":"rgb(192,192,192)","size":3.782914161682129},{"label":"http://www.oecd.org/unitedstates/","x":178.62994384765625,"y":-84.99417877197266,"id":"36","attributes":{"in_network":"false"},"color":"rgb(6,109,89)","size":2.446545124053955},{"label":"loc.gov","x":58.13777542114258,"y":80.01978302001953,"id":"77","attributes":{"ordine":"06","inlinksfromcrawl":"53","authority":"1302","in_network":"true","category":"GOV","tld":"gov","sldtld":"gov","knowledge":"0"},"color":"rgb(192,192,192)","size":8.246386528015137},{"label":"http://www.lib.washington.edu/about/news/newsletter/archive/e-news-winter-2015","x":0.9063563346862793,"y":197.81771850585938,"id":"102","attributes":{"in_network":"false"},"color":"rgb(6,109,89)","size":2.446545124053955},{"label":"http://www.oecd.org/turkey/","x":183.35794067382812,"y":-74.2464599609375,"id":"38","attributes":{"in_network":"false"},"color":"rgb(6,109,89)","size":2.446545124053955},{"label":"http://www.lib.washington.edu/about/strategicplan/2014/directions/teaching-learning","x":18.494436264038086,"y":196.95335388183594,"id":"99","attributes":{"in_network":"false"},"color":"rgb(6,109,89)","size":2.446545124053955},{"label":"http://www.lib.washington.edu/about/about/","x":-45.65205764770508,"y":192.4800262451172,"id":"110","attributes":{"in_network":"false"},"color":"rgb(6,109,89)","size":2.446545124053955},{"label":"http://www.soros.org/openaccess/read.shtml","x":130.09243774414062,"y":-149.0255889892578,"id":"25","attributes":{"in_network":"true"},"color":"rgb(6,109,89)","size":2.446545124053955},{"label":"http://www.loc.gov/","x":132.65408325195312,"y":146.75,"id":"78","attributes":{"in_network":"true"},"color":"rgb(6,109,89)","size":2.446545124053955},{"label":"http://www.mcgill.ca/library/services/otherloans","x":141.1269989013672,"y":138.6212158203125,"id":"75","attributes":{"in_network":"false"},"color":"rgb(6,109,89)","size":2.446545124053955},{"label":"henrystewartpublications.com","x":-111.51966094970703,"y":163.3892059326172,"id":"121","attributes":{"inlinksfromcrawl":"2","authority":"333","in_network":"true","category":"COM","tld":"com","sldtld":"com","knowledge":"0"},"color":"rgb(6,109,89)","size":3.929914951324463},{"label":"http://www.mcgill.ca/newsroom/socialmedia/","x":187.06822204589844,"y":64.32843017578125,"id":"60","attributes":{"in_network":"false"},"color":"rgb(6,109,89)","size":2.446545124053955},{"label":"http://www.questionpoint.org/crs/servlet/org.oclc.admin.BuildForm?\u0026page\u003dbanner\u0026type\u003d1\u0026language\u003d1\u0026institution\u003d10082","x":138.7048797607422,"y":-141.04476928710938,"id":"28","attributes":{"in_network":"false"},"color":"rgb(6,109,89)","size":2.446545124053955},{"label":"http://www.mcgill.ca/library/services/scholarly-publishing","x":163.45196533203125,"y":111.42765808105469,"id":"69","attributes":{"in_network":"false"},"color":"rgb(6,109,89)","size":2.446545124053955},{"label":"http://www.oecd-ilibrary.org/","x":194.73011779785156,"y":-34.825965881347656,"id":"46","attributes":{"in_network":"true"},"color":"rgb(6,109,89)","size":2.446545124053955},{"label":"http://www.allaboutcookies.org/","x":-112.53395080566406,"y":-162.69227600097656,"id":"172","attributes":{"authority":"210","in_network":"true"},"color":"rgb(6,109,89)","size":3.3820035457611084},{"label":"http://www.pinsentmasons.com/","x":150.99412536621094,"y":-127.8023681640625,"id":"30","attributes":{"in_network":"true"},"color":"rgb(6,109,89)","size":2.446545124053955},{"label":"http://www.lib.washington.edu/services/k12/public","x":75.29096221923828,"y":182.9315185546875,"id":"89","attributes":{"in_network":"false"},"color":"rgb(6,109,89)","size":2.446545124053955},{"label":"http://www.lib.umd.edu/tlc/equipment-policies","x":-94.99030303955078,"y":173.5209197998047,"id":"118","attributes":{"in_network":"false"},"color":"rgb(6,109,89)","size":2.446545124053955},{"label":"http://www.oecd.org/termsandconditions/","x":189.23411560058594,"y":-57.646514892578125,"id":"41","attributes":{"in_network":"false"},"color":"rgb(6,109,89)","size":2.446545124053955},{"label":"http://www.lib.umd.edu/","x":-67.18328857421875,"y":186.06201171875,"id":"113","attributes":{"authority":"220","in_network":"true"},"color":"rgb(6,109,89)","size":3.426549196243286},{"label":"twitter.com","x":-58.13777542114258,"y":-80.01978302001953,"id":"129","attributes":{"ordine":"01","inlinksfromcrawl":"1011","authority":"5063","in_network":"true","category":"COM","tld":"com","sldtld":"com","knowledge":"0"},"color":"rgb(47,122,178)","size":25.0},{"label":"http://firstsearch.oclc.org/","x":-153.61180114746094,"y":124.6438217163086,"id":"128","attributes":{"authority":"504","in_network":"true"},"color":"rgb(6,109,89)","size":4.69164514541626},{"label":"amturing.acm.org","x":-138.1864471435547,"y":-141.55271911621094,"id":"168","attributes":{"inlinksfromcrawl":"4","authority":"798","in_network":"true","category":"ORG","tld":"org","sldtld":"org","knowledge":"0"},"color":"rgb(192,192,192)","size":6.00128698348999},{"label":"http://www.lib.washington.edu/about/news/newsletter/news/","x":6.7767415046691895,"y":197.70367431640625,"id":"101","attributes":{"in_network":"false"},"color":"rgb(6,109,89)","size":2.446545124053955},{"label":"worldcat.org","x":1.2112969251221704E-14,"y":-197.81979370117188,"id":"0","attributes":{"ordine":"","inlinksfromcrawl":"9","authority":"115","in_network":"true","category":"ORG","tld":"org","sldtld":"org","knowledge":"2"},"color":"rgb(6,109,89)","size":2.958820104598999},{"label":"http://www.mcgill.ca/students/housing","x":192.04769897460938,"y":47.437828063964844,"id":"57","attributes":{"in_network":"false"},"color":"rgb(6,109,89)","size":2.446545124053955},{"label":"http://www.artstor.org","x":-190.35409545898438,"y":-53.83298110961914,"id":"152","attributes":{"in_network":"true"},"color":"rgb(6,109,89)","size":2.446545124053955},{"label":"http://www.henrystewartpublications.com/","x":-117.75463104248047,"y":158.95445251464844,"id":"122","attributes":{"in_network":"true"},"color":"rgb(6,109,89)","size":2.446545124053955},{"label":"hathitrust.org","x":-122.47055053710938,"y":155.35003662109375,"id":"123","attributes":{"inlinksfromcrawl":"10","authority":"12","in_network":"true","category":"ORG","tld":"org","sldtld":"org","knowledge":"0"},"color":"rgb(192,192,192)","size":2.5},{"label":"http://www.doaj.org/","x":-176.14817810058594,"y":90.0249252319336,"id":"133","attributes":{"in_network":"true"},"color":"rgb(6,109,89)","size":2.446545124053955},{"label":"http://www.washington.edu/admin/rules/policies/","x":35.649147033691406,"y":-194.5811004638672,"id":"7","attributes":{"in_network":"false"},"color":"rgb(6,109,89)","size":2.446545124053955},{"label":"http://www.lib.washington.edu/about/contact/contact-the-uw-libraries/","x":-34.15192413330078,"y":194.84947204589844,"id":"108","attributes":{"in_network":"false"},"color":"rgb(6,109,89)","size":2.446545124053955},{"label":"http://www.mcgill.ca/ssom/","x":190.55526733398438,"y":53.11647415161133,"id":"58","attributes":{"in_network":"false"},"color":"rgb(6,109,89)","size":2.446545124053955},{"label":"http://www.oecd.org/tax/","x":193.6107940673828,"y":-40.58977508544922,"id":"44","attributes":{"in_network":"false"},"color":"rgb(6,109,89)","size":2.446545124053955},{"label":"http://www.library.ucla.edu/","x":120.62806701660156,"y":156.78500366210938,"id":"80","attributes":{"in_network":"true"},"color":"rgb(6,109,89)","size":2.446545124053955},{"label":"http://www.lib.washington.edu/scholpub/options/change","x":64.30512237548828,"y":187.07623291015625,"id":"91","attributes":{"in_network":"false"},"color":"rgb(6,109,89)","size":2.446545124053955},{"label":"http://www.lib.washington.edu/help/consult/","x":35.93596649169922,"y":194.52833557128906,"id":"96","attributes":{"in_network":"false"},"color":"rgb(6,109,89)","size":2.446545124053955},{"label":"http://www.hathitrust.org/","x":-127.84882354736328,"y":150.9547882080078,"id":"124","attributes":{"authority":"189","in_network":"true"},"color":"rgb(192,192,192)","size":3.2884576320648193},{"label":"http://adt.caul.edu.au/","x":-7.500280857086182,"y":-197.67755126953125,"id":"187","attributes":{"authority":"190","in_network":"true"},"color":"rgb(6,109,89)","size":3.292912244796753},{"label":"pinsentmasons.com","x":145.00074768066406,"y":-134.56393432617188,"id":"29","attributes":{"inlinksfromcrawl":"2","authority":"592","in_network":"true","category":"COM","tld":"com","sldtld":"com","knowledge":"0"},"color":"rgb(192,192,192)","size":5.083646774291992},{"label":"http://www.mcgill.ca/library/services/open-access","x":136.95086669921875,"y":142.7484893798828,"id":"76","attributes":{"in_network":"false"},"color":"rgb(6,109,89)","size":2.446545124053955},{"label":"http://catalog.library.ucla.edu/","x":-197.8098602294922,"y":-1.9816524982452393,"id":"146","attributes":{"in_network":"true"},"color":"rgb(6,109,89)","size":2.446545124053955},{"label":"http://www.bl.uk/","x":-196.92172241210938,"y":-18.828216552734375,"id":"148","attributes":{"authority":"96","in_network":"true"},"color":"rgb(6,109,89)","size":2.874183416366577},{"label":"artstor.org","x":-192.39215087890625,"y":-46.020973205566406,"id":"151","attributes":{"inlinksfromcrawl":"2","authority":"412","in_network":"true","category":"ORG","tld":"org","sldtld":"org","knowledge":"1"},"color":"rgb(6,109,89)","size":4.281825065612793},{"label":"http://www.artstor.org/shared-shelf/subscribers?field_country_tid_selective\u003dAll\u0026field_state_province_tid_selective\u003dAll\u0026order\u003dtitle\u0026sort\u003ddesc","x":-169.3917999267578,"y":-102.17185974121094,"id":"161","attributes":{"in_network":"false"},"color":"rgb(6,109,89)","size":2.446545124053955},{"label":"http://www.oecd.org/trade/xcred/crc.htm","x":185.4806365966797,"y":-68.77210235595703,"id":"39","attributes":{"in_network":"false"},"color":"rgb(6,109,89)","size":2.446545124053955},{"label":"mcgill.worldcat.org","x":197.5386962890625,"y":10.541923522949219,"id":"51","attributes":{"inlinksfromcrawl":"114","authority":"168","in_network":"true","category":"ORG","tld":"org","sldtld":"org","knowledge":"1"},"color":"rgb(6,109,89)","size":3.1949119567871094},{"label":"http://www.lib.washington.edu/static/public/specialcollections/forms/funeralhome.html","x":86.01154327392578,"y":178.14231872558594,"id":"87","attributes":{"in_network":"false"},"color":"rgb(6,109,89)","size":2.446545124053955},{"label":"http://www.lib.washington.edu/be/seattle-links","x":24.3314208984375,"y":196.31773376464844,"id":"98","attributes":{"in_network":"false"},"color":"rgb(6,109,89)","size":2.446545124053955},{"label":"http://www.lib.washington.edu/static/public/specialcollections/forms/contact.html","x":80.6867904663086,"y":180.61647033691406,"id":"88","attributes":{"in_network":"false"},"color":"rgb(6,109,89)","size":2.446545124053955},{"label":"doaj.org","x":-172.0254364013672,"y":97.6725082397461,"id":"132","attributes":{"inlinksfromcrawl":"5","authority":"527","in_network":"true","category":"ORG","tld":"org","sldtld":"org","knowledge":"0"},"color":"rgb(6,109,89)","size":4.794100284576416},{"label":"http://www.ala.org/acrl/standards/ilframework","x":-94.62279510498047,"y":-173.7216033935547,"id":"174","attributes":{"in_network":"true"},"color":"rgb(6,109,89)","size":2.446545124053955},{"label":"http://www.lib.washington.edu/about/contacts.html","x":-28.35418701171875,"y":195.77719116210938,"id":"107","attributes":{"in_network":"false"},"color":"rgb(6,109,89)","size":2.446545124053955},{"label":"oecd.org","x":168.31658935546875,"y":-103.9336166381836,"id":"33","attributes":{"inlinksfromcrawl":"3","authority":"741","in_network":"true","category":"ORG","tld":"org","sldtld":"org","knowledge":"1"},"color":"rgb(6,109,89)","size":5.747376441955566},{"label":"http://www.ala.org/yaforum","x":-84.14932250976562,"y":-179.0294952392578,"id":"176","attributes":{"in_network":"false"},"color":"rgb(6,109,89)","size":2.446545124053955},{"label":"http://www.artstor.org/trial","x":-180.301513671875,"y":-81.38817596435547,"id":"157","attributes":{"in_network":"false"},"color":"rgb(6,109,89)","size":2.446545124053955},{"label":"soros.org","x":124.68923950195312,"y":-153.57493591308594,"id":"24","attributes":{"inlinksfromcrawl":"2","authority":"223","in_network":"true","category":"ORG","tld":"org","sldtld":"org","knowledge":"0"},"color":"rgb(6,109,89)","size":3.439912796020508},{"label":"washington.edu","x":58.13777542114258,"y":-80.01978302001953,"id":"2","attributes":{"ordine":"09","inlinksfromcrawl":"11","authority":"978","in_network":"true","category":"EDU","tld":"edu","sldtld":"edu","knowledge":"1"},"color":"rgb(6,109,89)","size":6.803108215332031},{"label":"http://www.lib.washington.edu/scholpub/actions/researchworks-services","x":47.413902282714844,"y":192.05361938476562,"id":"94","attributes":{"in_network":"false"},"color":"rgb(6,109,89)","size":2.446545124053955},{"label":"catalog.loc.gov","x":-196.36839294433594,"y":23.919057846069336,"id":"143","attributes":{"inlinksfromcrawl":"53","authority":"53","in_network":"true","category":"GOV","tld":"gov","sldtld":"gov","knowledge":"0"},"color":"rgb(6,109,89)","size":2.6826372146606445},{"label":"http://www.crl.edu/","x":-188.67259216308594,"y":59.45854949951172,"id":"138","attributes":{"authority":"89","in_network":"true"},"color":"rgb(6,109,89)","size":2.843001365661621},{"label":"http://www.oecd.org/youth.htm","x":176.02882385253906,"y":-90.2580795288086,"id":"35","attributes":{"in_network":"false"},"color":"rgb(6,109,89)","size":2.446545124053955},{"label":"http://www.library.ubc.ca/","x":101.51272583007812,"y":169.78761291503906,"id":"83","attributes":{"in_network":"true"},"color":"rgb(6,109,89)","size":2.446545124053955},{"label":"library.ucla.edu","x":126.74043273925781,"y":151.88656616210938,"id":"79","attributes":{"inlinksfromcrawl":"3","authority":"367","in_network":"true","category":"EDU","tld":"edu","sldtld":"edu","knowledge":"2"},"color":"rgb(6,109,89)","size":4.0813703536987305},{"label":"http://www.lib.washington.edu/about/news/newsletter/archive/e-news-spring-2014","x":-10.831637382507324,"y":197.5230255126953,"id":"104","attributes":{"in_network":"false"},"color":"rgb(6,109,89)","size":2.446545124053955},{"label":"http://www.washington.edu/students/","x":24.041980743408203,"y":-196.35337829589844,"id":"5","attributes":{"in_network":"false"},"color":"rgb(6,109,89)","size":2.446545124053955},{"label":"http://www.e-stat.go.jp/SG1/estat/eStatTopPortalE.do","x":-167.26048278808594,"y":105.62480163574219,"id":"131","attributes":{"authority":"109","in_network":"true"},"color":"rgb(6,109,89)","size":2.9320926666259766},{"label":"http://chroniclingamerica.loc.gov/","x":-194.55230712890625,"y":35.80600357055664,"id":"141","attributes":{"in_network":"true"},"color":"rgb(6,109,89)","size":2.446545124053955},{"label":"http://www.mcgill.ca/library/services/otherloans/othercatalogues/","x":149.1027069091797,"y":130.00405883789062,"id":"73","attributes":{"in_network":"false"},"color":"rgb(6,109,89)","size":2.446545124053955},{"label":"http://www.crl.edu/collections/topics/dissertations","x":-186.33648681640625,"y":66.4182357788086,"id":"137","attributes":{"authority":"186","in_network":"true"},"color":"rgb(6,109,89)","size":3.2750940322875977},{"label":"adt.caul.edu.au","x":-16.630910873413086,"y":-197.1194610595703,"id":"186","attributes":{"inlinksfromcrawl":"4","authority":"423","in_network":"true","category":"EDU","tld":"au","sldtld":"edu.au","knowledge":"0"},"color":"rgb(6,109,89)","size":4.3308258056640625},{"label":"lib.umd.edu","x":-58.75484848022461,"y":188.89292907714844,"id":"112","attributes":{"inlinksfromcrawl":"123","authority":"345","in_network":"true","category":"EDU","tld":"edu","sldtld":"edu","knowledge":"1"},"color":"rgb(6,109,89)","size":3.983369827270508},{"label":"http://www.lib.washington.edu/scholpub/actions/uw-libraries-support-for-open-access","x":53.09273910522461,"y":190.56187438964844,"id":"93","attributes":{"in_network":"false"},"color":"rgb(6,109,89)","size":2.446545124053955},{"label":"facebook.com","x":-94.06890106201172,"y":-30.564838409423828,"id":"188","attributes":{"ordine":"02","inlinksfromcrawl":"466","authority":"3615","in_network":"true","category":"COM","tld":"com","sldtld":"com","knowledge":"0"},"color":"rgb(47,122,178)","size":18.54979133605957},{"label":"mcgill.ca","x":194.63467407226562,"y":35.35553741455078,"id":"55","attributes":{"inlinksfromcrawl":"44","authority":"115","in_network":"true","category":"CA","tld":"ca","sldtld":"ca","knowledge":"1"},"color":"rgb(6,109,89)","size":2.958820104598999}],"edges":[{"source":"86","target":"3","id":"l1452","attributes":{},"color":"rgb(192,192,192)","size":1.0},{"source":"36","target":"46","id":"l542","attributes":{},"color":"rgb(192,192,192)","size":1.0},{"source":"64","target":"52","id":"l873","attributes":{},"color":"rgb(192,192,192)","size":1.0},{"source":"98","target":"19","id":"l1468","attributes":{},"color":"rgb(192,192,192)","size":1.0},{"source":"65","target":"52","id":"l874","attributes":{},"color":"rgb(192,192,192)","size":1.0},{"source":"152","target":"129","id":"843","attributes":{},"color":"rgb(192,192,192)","size":1.0},{"source":"176","target":"129","id":"299","attributes":{},"color":"rgb(192,192,192)","size":1.0},{"source":"154","target":"129","id":"785","attributes":{},"color":"rgb(192,192,192)","size":1.0},{"source":"39","target":"46","id":"l545","attributes":{},"color":"rgb(192,192,192)","size":1.0},{"source":"34","target":"46","id":"l6","attributes":{},"color":"rgb(192,192,192)","size":1.0},{"source":"116","target":"10","id":"l1486","attributes":{},"color":"rgb(192,192,192)","size":1.0},{"source":"56","target":"52","id":"l8","attributes":{},"color":"rgb(192,192,192)","size":1.0},{"source":"156","target":"129","id":"783","attributes":{},"color":"rgb(192,192,192)","size":1.0},{"source":"72","target":"52","id":"l883","attributes":{},"color":"rgb(192,192,192)","size":1.0},{"source":"28","target":"85","id":"l540","attributes":{},"color":"rgb(192,192,192)","size":1.0},{"source":"137","target":"48","id":"l13","attributes":{},"color":"rgb(192,192,192)","size":1.0},{"source":"161","target":"129","id":"778","attributes":{},"color":"rgb(192,192,192)","size":1.0},{"source":"80","target":"146","id":"l10","attributes":{},"color":"rgb(192,192,192)","size":1.0},{"source":"177","target":"167","id":"l2493","attributes":{},"color":"rgb(192,192,192)","size":1.0},{"source":"1","target":"129","id":"293","attributes":{},"color":"rgb(192,192,192)","size":1.0},{"source":"109","target":"27","id":"l1479","attributes":{},"color":"rgb(192,192,192)","size":1.0},{"source":"110","target":"167","id":"l1480","attributes":{},"color":"rgb(192,192,192)","size":1.0},{"source":"21","target":"141","id":"l536","attributes":{},"color":"rgb(192,192,192)","size":1.0},{"source":"165","target":"129","id":"774","attributes":{},"color":"rgb(192,192,192)","size":1.0},{"source":"62","target":"50","id":"l871","attributes":{},"color":"rgb(192,192,192)","size":1.0},{"source":"180","target":"129","id":"296","attributes":{},"color":"rgb(192,192,192)","size":1.0},{"source":"95","target":"19","id":"l1465","attributes":{},"color":"rgb(192,192,192)","size":1.0},{"source":"15","target":"80","id":"l531","attributes":{},"color":"rgb(192,192,192)","size":1.0},{"source":"81","target":"13","id":"l1451","attributes":{},"color":"rgb(192,192,192)","size":1.0},{"source":"95","target":"128","id":"l1464","attributes":{},"color":"rgb(192,192,192)","size":1.0},{"source":"23","target":"85","id":"l539","attributes":{},"color":"rgb(192,192,192)","size":1.0},{"source":"158","target":"129","id":"781","attributes":{},"color":"rgb(192,192,192)","size":1.0},{"source":"22","target":"141","id":"l537","attributes":{},"color":"rgb(192,192,192)","size":1.0},{"source":"38","target":"46","id":"l544","attributes":{},"color":"rgb(192,192,192)","size":1.0},{"source":"118","target":"10","id":"l1488","attributes":{},"color":"rgb(192,192,192)","size":1.0},{"source":"153","target":"129","id":"786","attributes":{},"color":"rgb(192,192,192)","size":1.0},{"source":"63","target":"52","id":"l872","attributes":{},"color":"rgb(192,192,192)","size":1.0},{"source":"181","target":"56","id":"l2497","attributes":{},"color":"rgb(192,192,192)","size":1.0},{"source":"73","target":"148","id":"l888","attributes":{},"color":"rgb(192,192,192)","size":1.0},{"source":"44","target":"46","id":"l550","attributes":{},"color":"rgb(192,192,192)","size":1.0},{"source":"53","target":"56","id":"l838","attributes":{},"color":"rgb(192,192,192)","size":1.0},{"source":"73","target":"1","id":"l889","attributes":{},"color":"rgb(192,192,192)","size":1.0},{"source":"137","target":"187","id":"l14","attributes":{},"color":"rgb(192,192,192)","size":1.0},{"source":"141","target":"144","id":"l16","attributes":{},"color":"rgb(192,192,192)","size":1.0},{"source":"102","target":"3","id":"l1472","attributes":{},"color":"rgb(192,192,192)","size":1.0},{"source":"83","target":"188","id":"1","attributes":{},"color":"rgb(192,192,192)","size":1.0},{"source":"43","target":"46","id":"l549","attributes":{},"color":"rgb(192,192,192)","size":1.0},{"source":"66","target":"52","id":"l875","attributes":{},"color":"rgb(192,192,192)","size":1.0},{"source":"164","target":"129","id":"775","attributes":{},"color":"rgb(192,192,192)","size":1.0},{"source":"92","target":"133","id":"l1459","attributes":{},"color":"rgb(192,192,192)","size":1.0},{"source":"96","target":"3","id":"l1466","attributes":{},"color":"rgb(192,192,192)","size":1.0},{"source":"7","target":"85","id":"l418","attributes":{},"color":"rgb(192,192,192)","size":1.0},{"source":"20","target":"141","id":"l534","attributes":{},"color":"rgb(192,192,192)","size":1.0},{"source":"113","target":"10","id":"l12","attributes":{},"color":"rgb(192,192,192)","size":1.0},{"source":"5","target":"85","id":"l416","attributes":{},"color":"rgb(192,192,192)","size":1.0},{"source":"104","target":"3","id":"l1474","attributes":{},"color":"rgb(192,192,192)","size":1.0},{"source":"15","target":"146","id":"l530","attributes":{},"color":"rgb(192,192,192)","size":1.0},{"source":"14","target":"146","id":"l528","attributes":{},"color":"rgb(192,192,192)","size":1.0},{"source":"37","target":"46","id":"l543","attributes":{},"color":"rgb(192,192,192)","size":1.0},{"source":"160","target":"129","id":"779","attributes":{},"color":"rgb(192,192,192)","size":1.0},{"source":"75","target":"52","id":"l893","attributes":{},"color":"rgb(192,192,192)","size":1.0},{"source":"69","target":"52","id":"l878","attributes":{},"color":"rgb(192,192,192)","size":1.0},{"source":"110","target":"124","id":"l1481","attributes":{},"color":"rgb(192,192,192)","size":1.0},{"source":"73","target":"138","id":"l890","attributes":{},"color":"rgb(192,192,192)","size":1.0},{"source":"106","target":"3","id":"l1476","attributes":{},"color":"rgb(192,192,192)","size":1.0},{"source":"71","target":"124","id":"l881","attributes":{},"color":"rgb(192,192,192)","size":1.0},{"source":"70","target":"52","id":"l879","attributes":{},"color":"rgb(192,192,192)","size":1.0},{"source":"97","target":"83","id":"l1467","attributes":{},"color":"rgb(192,192,192)","size":1.0},{"source":"178","target":"129","id":"298","attributes":{},"color":"rgb(192,192,192)","size":1.0},{"source":"183","target":"129","id":"294","attributes":{},"color":"rgb(192,192,192)","size":1.0},{"source":"139","target":"187","id":"l1853","attributes":{},"color":"rgb(192,192,192)","size":1.0},{"source":"42","target":"46","id":"l548","attributes":{},"color":"rgb(192,192,192)","size":1.0},{"source":"175","target":"129","id":"300","attributes":{},"color":"rgb(192,192,192)","size":1.0},{"source":"10","target":"113","id":"l3","attributes":{},"color":"rgb(192,192,192)","size":1.0},{"source":"92","target":"150","id":"l1460","attributes":{},"color":"rgb(192,192,192)","size":1.0},{"source":"32","target":"46","id":"l5","attributes":{},"color":"rgb(192,192,192)","size":1.0},{"source":"67","target":"52","id":"l876","attributes":{},"color":"rgb(192,192,192)","size":1.0},{"source":"157","target":"129","id":"782","attributes":{},"color":"rgb(192,192,192)","size":1.0},{"source":"179","target":"129","id":"297","attributes":{},"color":"rgb(192,192,192)","size":1.0},{"source":"99","target":"174","id":"l1469","attributes":{},"color":"rgb(192,192,192)","size":1.0},{"source":"87","target":"3","id":"l1453","attributes":{},"color":"rgb(192,192,192)","size":1.0},{"source":"142","target":"129","id":"835","attributes":{},"color":"rgb(192,192,192)","size":1.0},{"source":"141","target":"78","id":"l17","attributes":{},"color":"rgb(192,192,192)","size":1.0},{"source":"54","target":"56","id":"l839","attributes":{},"color":"rgb(192,192,192)","size":1.0},{"source":"73","target":"144","id":"l891","attributes":{},"color":"rgb(192,192,192)","size":1.0},{"source":"76","target":"52","id":"l894","attributes":{},"color":"rgb(192,192,192)","size":1.0},{"source":"52","target":"56","id":"l7","attributes":{},"color":"rgb(192,192,192)","size":1.0},{"source":"115","target":"10","id":"l1485","attributes":{},"color":"rgb(192,192,192)","size":1.0},{"source":"155","target":"129","id":"784","attributes":{},"color":"rgb(192,192,192)","size":1.0},{"source":"139","target":"48","id":"l1854","attributes":{},"color":"rgb(192,192,192)","size":1.0},{"source":"59","target":"129","id":"840","attributes":{},"color":"rgb(192,192,192)","size":1.0},{"source":"103","target":"3","id":"l1473","attributes":{},"color":"rgb(192,192,192)","size":1.0},{"source":"60","target":"129","id":"839","attributes":{},"color":"rgb(192,192,192)","size":1.0},{"source":"73","target":"78","id":"l884","attributes":{},"color":"rgb(192,192,192)","size":1.0},{"source":"74","target":"52","id":"l892","attributes":{},"color":"rgb(192,192,192)","size":1.0},{"source":"120","target":"10","id":"l1490","attributes":{},"color":"rgb(192,192,192)","size":1.0},{"source":"93","target":"150","id":"l1461","attributes":{},"color":"rgb(192,192,192)","size":1.0},{"source":"32","target":"34","id":"l4","attributes":{},"color":"rgb(192,192,192)","size":1.0},{"source":"88","target":"3","id":"l1454","attributes":{},"color":"rgb(192,192,192)","size":1.0},{"source":"57","target":"129","id":"842","attributes":{},"color":"rgb(192,192,192)","size":1.0},{"source":"73","target":"52","id":"l885","attributes":{},"color":"rgb(192,192,192)","size":1.0},{"source":"71","target":"138","id":"l882","attributes":{},"color":"rgb(192,192,192)","size":1.0},{"source":"71","target":"52","id":"l880","attributes":{},"color":"rgb(192,192,192)","size":1.0},{"source":"114","target":"10","id":"l1484","attributes":{},"color":"rgb(192,192,192)","size":1.0},{"source":"17","target":"169","id":"l533","attributes":{},"color":"rgb(192,192,192)","size":1.0},{"source":"90","target":"3","id":"l1456","attributes":{},"color":"rgb(192,192,192)","size":1.0},{"source":"94","target":"3","id":"l1462","attributes":{},"color":"rgb(192,192,192)","size":1.0},{"source":"16","target":"170","id":"l532","attributes":{},"color":"rgb(192,192,192)","size":1.0},{"source":"23","target":"1","id":"l538","attributes":{},"color":"rgb(192,192,192)","size":1.0},{"source":"6","target":"85","id":"l417","attributes":{},"color":"rgb(192,192,192)","size":1.0},{"source":"141","target":"129","id":"844","attributes":{},"color":"rgb(192,192,192)","size":1.0},{"source":"111","target":"124","id":"l1483","attributes":{},"color":"rgb(192,192,192)","size":1.0},{"source":"163","target":"129","id":"776","attributes":{},"color":"rgb(192,192,192)","size":1.0},{"source":"61","target":"129","id":"838","attributes":{},"color":"rgb(192,192,192)","size":1.0},{"source":"108","target":"27","id":"l1478","attributes":{},"color":"rgb(192,192,192)","size":1.0},{"source":"142","target":"144","id":"l1855","attributes":{},"color":"rgb(192,192,192)","size":1.0},{"source":"14","target":"80","id":"l529","attributes":{},"color":"rgb(192,192,192)","size":1.0},{"source":"8","target":"85","id":"l419","attributes":{},"color":"rgb(192,192,192)","size":1.0},{"source":"119","target":"10","id":"l1489","attributes":{},"color":"rgb(192,192,192)","size":1.0},{"source":"3","target":"85","id":"l2","attributes":{},"color":"rgb(192,192,192)","size":1.0},{"source":"182","target":"129","id":"295","attributes":{},"color":"rgb(192,192,192)","size":1.0},{"source":"4","target":"85","id":"l415","attributes":{},"color":"rgb(192,192,192)","size":1.0},{"source":"91","target":"133","id":"l1457","attributes":{},"color":"rgb(192,192,192)","size":1.0},{"source":"117","target":"10","id":"l1487","attributes":{},"color":"rgb(192,192,192)","size":1.0},{"source":"41","target":"46","id":"l547","attributes":{},"color":"rgb(192,192,192)","size":1.0},{"source":"142","target":"78","id":"l1857","attributes":{},"color":"rgb(192,192,192)","size":1.0},{"source":"89","target":"19","id":"l1455","attributes":{},"color":"rgb(192,192,192)","size":1.0},{"source":"1","target":"188","id":"147","attributes":{},"color":"rgb(192,192,192)","size":1.0},{"source":"105","target":"83","id":"l1475","attributes":{},"color":"rgb(192,192,192)","size":1.0},{"source":"100","target":"174","id":"l1470","attributes":{},"color":"rgb(192,192,192)","size":1.0},{"source":"35","target":"46","id":"l541","attributes":{},"color":"rgb(192,192,192)","size":1.0},{"source":"58","target":"129","id":"841","attributes":{},"color":"rgb(192,192,192)","size":1.0},{"source":"92","target":"25","id":"l1458","attributes":{},"color":"rgb(192,192,192)","size":1.0},{"source":"11","target":"113","id":"l527","attributes":{},"color":"rgb(192,192,192)","size":1.0},{"source":"20","target":"133","id":"l535","attributes":{},"color":"rgb(192,192,192)","size":1.0},{"source":"159","target":"129","id":"780","attributes":{},"color":"rgb(192,192,192)","size":1.0},{"source":"40","target":"46","id":"l546","attributes":{},"color":"rgb(192,192,192)","size":1.0},{"source":"111","target":"167","id":"l1482","attributes":{},"color":"rgb(192,192,192)","size":1.0},{"source":"162","target":"129","id":"777","attributes":{},"color":"rgb(192,192,192)","size":1.0},{"source":"68","target":"52","id":"l877","attributes":{},"color":"rgb(192,192,192)","size":1.0},{"source":"172","target":"30","id":"l19","attributes":{},"color":"rgb(192,192,192)","size":1.0},{"source":"73","target":"83","id":"l887","attributes":{},"color":"rgb(192,192,192)","size":1.0},{"source":"101","target":"83","id":"l1471","attributes":{},"color":"rgb(192,192,192)","size":1.0},{"source":"94","target":"27","id":"l1463","attributes":{},"color":"rgb(192,192,192)","size":1.0},{"source":"107","target":"27","id":"l1477","attributes":{},"color":"rgb(192,192,192)","size":1.0},{"source":"80","target":"13","id":"l9","attributes":{},"color":"rgb(192,192,192)","size":1.0},{"source":"73","target":"167","id":"l886","attributes":{},"color":"rgb(192,192,192)","size":1.0}]}